test_gradio_client.py
sinapsis_data_readers/__init__.py
sinapsis_data_readers/helpers/__init__.py
sinapsis_data_readers/helpers/coco_dataclasses.py
sinapsis_data_readers/helpers/csv_reader.py
sinapsis_data_readers/helpers/file_path_helpers.py
sinapsis_data_readers/helpers/sklearn_dataset_subset.py
sinapsis_data_readers/helpers/sktime_datasets_subset.py
sinapsis_data_readers/helpers/tags.py
sinapsis_data_readers/helpers/text_input_helpers.py
sinapsis_data_readers/templates/__init__.py
sinapsis_data_readers/templates/base_file_data_loader.py
sinapsis_data_readers/templates/audio_readers/__init__.py
sinapsis_data_readers/templates/audio_readers/audio_reader_pydub.py
sinapsis_data_readers/templates/audio_readers/audio_reader_soundfile.py
sinapsis_data_readers/templates/audio_readers/audio_reader_to_bytes.py
sinapsis_data_readers/templates/audio_readers/base_audio_reader.py
sinapsis_data_readers/templates/datasets_readers/__init__.py
sinapsis_data_readers/templates/datasets_readers/csv_datasets.py
sinapsis_data_readers/templates/datasets_readers/dataset_splitter.py
sinapsis_data_readers/templates/datasets_readers/sklearn_datasets.py
sinapsis_data_readers/templates/datasets_readers/sktime_datasets.py
sinapsis_data_readers/templates/image_readers/__init__.py
sinapsis_data_readers/templates/image_readers/base_image_folder_data_loader.py
sinapsis_data_readers/templates/image_readers/coco_dataset_reader.py
sinapsis_data_readers/templates/image_readers/csv_dataset_reader.py
sinapsis_data_readers/templates/image_readers/image_folder_reader_cv2.py
sinapsis_data_readers/templates/image_readers/image_folder_reader_kornia.py
sinapsis_data_readers/templates/text_readers/__init__.py
sinapsis_data_readers/templates/text_readers/text_input.py
sinapsis_data_readers/templates/video_readers/__init__.py
sinapsis_data_readers/templates/video_readers/base_video_reader.py
sinapsis_data_readers/templates/video_readers/video_reader_cv2.py
sinapsis_data_readers-0.1.23.dist-info/licenses/LICENSE
sinapsis_data_readers-0.1.23.dist-info/METADATA
sinapsis_data_readers-0.1.23.dist-info/WHEEL
sinapsis_data_readers-0.1.23.dist-info/top_level.txt
sinapsis_data_readers-0.1.23.dist-info/RECORD
