Metadata-Version: 2.4
Name: sinapsis-data-readers
Version: 0.1.23
Summary: Templates to read data in different formats
Author-email: SinapsisAI <dev@sinapsis.tech>
Project-URL: Homepage, https://sinapsis.tech
Project-URL: Documentation, https://docs.sinapsis.tech/docs
Project-URL: Tutorials, https://docs.sinapsis.tech/tutorials
Project-URL: Repository, https://github.com/Sinapsis-AI/sinapsis-data-tools.git
Requires-Python: >=3.10
License-File: LICENSE
Requires-Dist: sinapsis>=0.1.1
Provides-Extra: nvidia-dali
Requires-Dist: nvidia-dali-cuda120>=1.43.0; extra == "nvidia-dali"
Provides-Extra: torch-codec
Requires-Dist: torch>=2.4.1; extra == "torch-codec"
Requires-Dist: torchcodec>=0.0.3; extra == "torch-codec"
Provides-Extra: sklearn-datasets
Requires-Dist: pandas>=2.2.3; extra == "sklearn-datasets"
Requires-Dist: scikit-learn>=1.5.2; extra == "sklearn-datasets"
Provides-Extra: sktime-datareaders
Requires-Dist: sktime>=0.34.0; extra == "sktime-datareaders"
Provides-Extra: coco-dataset
Requires-Dist: pycocotools>=2.0.8; extra == "coco-dataset"
Provides-Extra: soundfile
Requires-Dist: soundfile>=0.12.1; extra == "soundfile"
Provides-Extra: pydub
Requires-Dist: pydub>=0.25.1; extra == "pydub"
Requires-Dist: soundfile>=0.12.1; extra == "pydub"
Provides-Extra: all
Requires-Dist: sinapsis-data-readers[coco-dataset,ffmpeg,nvidia-dali,opencv,pydub,sklearn-datasets,sktime-datareaders,soundfile,torch-codec]; extra == "all"
Provides-Extra: opencv
Requires-Dist: opencv-python-headless>=4.11.0.86; extra == "opencv"
Provides-Extra: ffmpeg
Requires-Dist: ffmpeg-python>=0.2.0; extra == "ffmpeg"
Provides-Extra: kornia
Requires-Dist: kornia>=0.8.1; extra == "kornia"
Requires-Dist: kornia-rs>=0.1.9; extra == "kornia"
Requires-Dist: pillow>=11.2.1; extra == "kornia"
Dynamic: license-file
